README.rst
setup.py
shuiyuan/__init__.py
shuiyuan.egg-info/PKG-INFO
shuiyuan.egg-info/SOURCES.txt
shuiyuan.egg-info/dependency_links.txt
shuiyuan.egg-info/requires.txt
shuiyuan.egg-info/top_level.txt