Metadata-Version: 1.1
Name: shuiyuan
Version: 0.0.2
Summary: small package description
Home-page: https://github.com/dengyongqing/shuiyuan
Author: jason
Author-email: dengyongqing@aliyun.com
License: MIT
Download-URL: https://github.com/dengyongqing/shuiyuan/archive/0.0.2.tar.gz
Keywords: key1,key2,key3
Platform: UNKNOWN
Classifier: Development Status :: 5 - Production/Stable
Classifier: License :: OSI Approved :: MIT License
Classifier: Natural Language :: English
Classifier: Programming Language :: Python
Classifier: Programming Language :: Python :: 2.7
Classifier: Programming Language :: Python :: 3.6
Classifier: Topic :: Internet :: WWW/HTTP :: Browsers
